<?xml version="1.0" encoding="utf-8" ?>
<dwsync>
<file name=".gitignore" server="www.jarbrain.com//" local="130189760555110488" remote="130143138000000000" Dst="2" />
<file name="README.txt" server="www.jarbrain.com//" local="130189760566601145" remote="130143138000000000" Dst="2" />
<file name="LICENSE.txt" server="www.jarbrain.com//" local="130189760566641147" remote="130143138000000000" Dst="2" />
<file name="README_devel_node_access.txt" server="www.jarbrain.com//" local="130189760566691150" remote="130143138000000000" Dst="2" />
<file name="devel-rtl.css" server="www.jarbrain.com//" local="130189760576621718" remote="130143138000000000" Dst="2" />
<file name="devel.css" server="www.jarbrain.com//" local="130189760576621718" remote="130143138000000000" Dst="2" />
<file name="devel.admin.inc" server="www.jarbrain.com//" local="130189760576681722" remote="130143138000000000" Dst="2" />
<file name="devel.info" server="www.jarbrain.com//" local="130189760589332445" remote="130143138000000000" Dst="2" />
<file name="devel.drush.inc" server="www.jarbrain.com//" local="130189760589372448" remote="130143138000000000" Dst="2" />
<file name="devel.install" server="www.jarbrain.com//" local="130189760589402449" remote="130143138000000000" Dst="2" />
<file name="devel.js" server="www.jarbrain.com//" local="130189760600753099" remote="130143138000000000" Dst="2" />
<file name="devel.mail.inc" server="www.jarbrain.com//" local="130189760600763099" remote="130143138000000000" Dst="2" />
<file name="devel.pages.inc" server="www.jarbrain.com//" local="130189760607973512" remote="130143138000000000" Dst="2" />
<file name="devel.module" server="www.jarbrain.com//" local="130189760608013514" remote="130143138000000000" Dst="2" />
<file name="devel.rules.inc" server="www.jarbrain.com//" local="130189760608213525" remote="130143138000000000" Dst="2" />
<file name="devel.test" server="www.jarbrain.com//" local="130189760620764243" remote="130143138000000000" Dst="2" />
<file name="develDrushTest.php" server="www.jarbrain.com//" local="130189760620804245" remote="130143138000000000" Dst="2" />
<file name="devel_krumo_path.js" server="www.jarbrain.com//" local="130189760667636924" remote="130143138000000000" Dst="2" />
<file name="devel_node_access.info" server="www.jarbrain.com//" local="130189760680057635" remote="130143138000000000" Dst="2" />
<file name="devel_node_access.api.php" server="www.jarbrain.com//" local="130189760680117638" remote="130143138000000000" Dst="2" />
<file name="devel_node_access.install" server="www.jarbrain.com//" local="130189760680227644" remote="130143138000000000" Dst="2" />
<file name="devel_node_access.js" server="www.jarbrain.com//" local="130189760693908427" remote="130143138000000000" Dst="2" />
<file name="devel_node_access.module" server="www.jarbrain.com//" local="130189760693928428" remote="130143138000000000" Dst="2" />
<file name="jquery-1.4.4-uncompressed.js" server="www.jarbrain.com//" local="130189760713719560" remote="130143138000000000" Dst="2" />
</dwsync>