<?xml version="1.0" encoding="utf-8" ?>
<dwsync>
<file name="about.html" server="www.jarbrain.com//" local="130189765252619170" remote="130143148200000000" Dst="2" />
<file name="advanced-settings.html" server="www.jarbrain.com//" local="130189765252659172" remote="130143148200000000" Dst="2" />
<file name="advanced-style-settings.html" server="www.jarbrain.com//" local="130189765262429731" remote="130143148200000000" Dst="2" />
<file name="aggregation.html" server="www.jarbrain.com//" local="130189765262469733" remote="130143148200000000" Dst="2" />
<file name="alter-exposed-filter.html" server="www.jarbrain.com//" local="130189765262559739" remote="130143148200000000" Dst="2" />
<file name="analyze-theme.html" server="www.jarbrain.com//" local="130189765272330297" remote="130143148200000000" Dst="2" />
<file name="api-default-views.html" server="www.jarbrain.com//" local="130189765272330297" remote="130143148200000000" Dst="2" />
<file name="api-example.html" server="www.jarbrain.com//" local="130189765272340298" remote="130143148200000000" Dst="2" />
<file name="api-forms.html" server="www.jarbrain.com//" local="130189765282330869" remote="130143148200000000" Dst="2" />
<file name="api-handler-area.html" server="www.jarbrain.com//" local="130189765282370872" remote="130143148200000000" Dst="2" />
<file name="api-tables.html" server="www.jarbrain.com//" local="130189765282390873" remote="130143148200000000" Dst="2" />
<file name="api-upgrading.html" server="www.jarbrain.com//" local="130189765292101428" remote="130143148200000000" Dst="2" />
<file name="api.html" server="www.jarbrain.com//" local="130189765292141431" remote="130143148200000000" Dst="2" />
<file name="argument.html" server="www.jarbrain.com//" local="130189765292301440" remote="130143148200000000" Dst="2" />
<file name="basic-settings.html" server="www.jarbrain.com//" local="130189765302041997" remote="130143148200000000" Dst="2" />
<file name="demo-video.html" server="www.jarbrain.com//" local="130189765302081999" remote="130143148200000000" Dst="2" />
<file name="display-attachment.html" server="www.jarbrain.com//" local="130189765302142003" remote="130143148200000000" Dst="2" />
<file name="display-block.html" server="www.jarbrain.com//" local="130189765312142575" remote="130143148200000000" Dst="2" />
<file name="display-default.html" server="www.jarbrain.com//" local="130189765312182577" remote="130143148200000000" Dst="2" />
<file name="display-feed.html" server="www.jarbrain.com//" local="130189765312292583" remote="130143148200000000" Dst="2" />
<file name="display-page.html" server="www.jarbrain.com//" local="130189765322033140" remote="130143148200000000" Dst="2" />
<file name="display.html" server="www.jarbrain.com//" local="130189765322053141" remote="130143148200000000" Dst="2" />
<file name="drush.html" server="www.jarbrain.com//" local="130189765322113145" remote="130143148200000000" Dst="2" />
<file name="embed.html" server="www.jarbrain.com//" local="130189765338304071" remote="130143148200000000" Dst="2" />
<file name="empty-text.html" server="www.jarbrain.com//" local="130189765338364074" remote="130143148200000000" Dst="2" />
<file name="example-author-block.html" server="www.jarbrain.com//" local="130189765338744096" remote="130143148200000000" Dst="2" />
<file name="example-filter-by-current-user.html" server="www.jarbrain.com//" local="130189765348184636" remote="130143148200000000" Dst="2" />
<file name="example-slideshow-thumb-pager.html" server="www.jarbrain.com//" local="130189765348184636" remote="130143148200000000" Dst="2" />
<file name="example-recent-stories.html" server="www.jarbrain.com//" local="130189765348224638" remote="130143148200000000" Dst="2" />
<file name="example-user-feed.html" server="www.jarbrain.com//" local="130189765358185208" remote="130143148200000000" Dst="2" />
<file name="example-users-by-role.html" server="www.jarbrain.com//" local="130189765358185208" remote="130143148200000000" Dst="2" />
<file name="exposed-form.html" server="www.jarbrain.com//" local="130189765358305215" remote="130143148200000000" Dst="2" />
<file name="field.html" server="www.jarbrain.com//" local="130189765368265785" remote="130143148200000000" Dst="2" />
<file name="filter.html" server="www.jarbrain.com//" local="130189765368305787" remote="130143148200000000" Dst="2" />
<file name="get-total-rows.html" server="www.jarbrain.com//" local="130189765368455796" remote="130143148200000000" Dst="2" />
<file name="group-by.html" server="www.jarbrain.com//" local="130189765378346361" remote="130143148200000000" Dst="2" />
<file name="getting-started.html" server="www.jarbrain.com//" local="130189765378396364" remote="130143148200000000" Dst="2" />
<file name="header.html" server="www.jarbrain.com//" local="130189765378396364" remote="130143148200000000" Dst="2" />
<file name="misc-notes.html" server="www.jarbrain.com//" local="130189765516504263" remote="130143148200000000" Dst="2" />
<file name="menu.html" server="www.jarbrain.com//" local="130189765516544266" remote="130143148200000000" Dst="2" />
<file name="new.html" server="www.jarbrain.com//" local="130189765527884914" remote="130143148200000000" Dst="2" />
<file name="other-help.html" server="www.jarbrain.com//" local="130189765527884914" remote="130143148200000000" Dst="2" />
<file name="overrides.html" server="www.jarbrain.com//" local="130189765528024922" remote="130143148200000000" Dst="2" />
<file name="performance-views-vs-displays.html" server="www.jarbrain.com//" local="130189765539255565" remote="130143148200000000" Dst="2" />
<file name="performance.html" server="www.jarbrain.com//" local="130189765539255565" remote="130143148200000000" Dst="2" />
<file name="path.html" server="www.jarbrain.com//" local="130189765539295567" remote="130143148200000000" Dst="2" />
<file name="relationship-representative.html" server="www.jarbrain.com//" local="130189765549046125" remote="130143148200000000" Dst="2" />
<file name="relationship.html" server="www.jarbrain.com//" local="130189765549056125" remote="130143148200000000" Dst="2" />
<file name="reports.html" server="www.jarbrain.com//" local="130189765549456148" remote="130143148200000000" Dst="2" />
<file name="select-multple-nids-contextual-filters.html" server="www.jarbrain.com//" local="130189765558836685" remote="130143148200000000" Dst="2" />
<file name="semantic-views.html" server="www.jarbrain.com//" local="130189765558836685" remote="130143148200000000" Dst="2" />
<file name="sort.html" server="www.jarbrain.com//" local="130189765558986693" remote="130143148200000000" Dst="2" />
<file name="style-comment-rss.html" server="www.jarbrain.com//" local="130189765569477293" remote="130143148200000000" Dst="2" />
<file name="style-fields.html" server="www.jarbrain.com//" local="130189765569517296" remote="130143148200000000" Dst="2" />
<file name="style-grid.html" server="www.jarbrain.com//" local="130189765569517296" remote="130143148200000000" Dst="2" />
<file name="style-grouping.html" server="www.jarbrain.com//" local="130189765580277911" remote="130143148200000000" Dst="2" />
<file name="style-list.html" server="www.jarbrain.com//" local="130189765580287912" remote="130143148200000000" Dst="2" />
<file name="style-jump.html" server="www.jarbrain.com//" local="130189765580327914" remote="130143148200000000" Dst="2" />
<file name="style-node-rss.html" server="www.jarbrain.com//" local="130189765590138475" remote="130143148200000000" Dst="2" />
<file name="style-node.html" server="www.jarbrain.com//" local="130189765590138475" remote="130143148200000000" Dst="2" />
<file name="style-row.html" server="www.jarbrain.com//" local="130189765590148476" remote="130143148200000000" Dst="2" />
<file name="style-rss.html" server="www.jarbrain.com//" local="130189765599999039" remote="130143148200000000" Dst="2" />
<file name="style-settings.html" server="www.jarbrain.com//" local="130189765600049042" remote="130143148200000000" Dst="2" />
<file name="style-summary-unformatted.html" server="www.jarbrain.com//" local="130189765600129046" remote="130143148200000000" Dst="2" />
<file name="style-table.html" server="www.jarbrain.com//" local="130189765609729596" remote="130143148200000000" Dst="2" />
<file name="style-unformatted.html" server="www.jarbrain.com//" local="130189765609729596" remote="130143148200000000" Dst="2" />
<file name="style-summary.html" server="www.jarbrain.com//" local="130189765609769598" remote="130143148200000000" Dst="2" />
<file name="style.html" server="www.jarbrain.com//" local="130189765619670164" remote="130143148200000000" Dst="2" />
<file name="taxonomy-page-override.html" server="www.jarbrain.com//" local="130189765619710166" remote="130143148200000000" Dst="2" />
<file name="theme-css.html" server="www.jarbrain.com//" local="130189765619830173" remote="130143148200000000" Dst="2" />
<file name="top-pager.html" server="www.jarbrain.com//" local="130189765629520728" remote="130143148200000000" Dst="2" />
<file name="ui-crashes.html" server="www.jarbrain.com//" local="130189765629560730" remote="130143148200000000" Dst="2" />
<file name="updating-view3.html" server="www.jarbrain.com//" local="130189765629630734" remote="130143148200000000" Dst="2" />
<file name="updating.html" server="www.jarbrain.com//" local="130189765639621305" remote="130143148200000000" Dst="2" />
<file name="upgrading.html" server="www.jarbrain.com//" local="130189765639681309" remote="130143148200000000" Dst="2" />
<file name="using-theme.html" server="www.jarbrain.com//" local="130189765639721311" remote="130143148200000000" Dst="2" />
<file name="view-add.html" server="www.jarbrain.com//" local="130189765649711882" remote="130143148200000000" Dst="2" />
<file name="view-settings.html" server="www.jarbrain.com//" local="130189765649711882" remote="130143148200000000" Dst="2" />
<file name="view-type.html" server="www.jarbrain.com//" local="130189765649711882" remote="130143148200000000" Dst="2" />
<file name="views.help.ini" server="www.jarbrain.com//" local="130189765663792688" remote="130143148200000000" Dst="2" />
</dwsync>